topsis/__init__.py
topsis/topsis.py
102218038_topsis-3.0.0.dist-info/METADATA
102218038_topsis-3.0.0.dist-info/WHEEL
102218038_topsis-3.0.0.dist-info/top_level.txt
102218038_topsis-3.0.0.dist-info/RECORD
