Metadata-Version: 2.1
Name: 102218038-topsis
Version: 3.0.0
Summary: Runs topsis algorythm for pre trained models
Author: thebrownkidd
Keywords: python,topsis,machine learning
Classifier: Development Status :: 1 - Planning
Classifier: Intended Audience :: Developers
Classifier: Programming Language :: Python :: 3
Classifier: Operating System :: Unix
Classifier: Operating System :: MacOS :: MacOS X
Classifier: Operating System :: Microsoft :: Windows
Requires-Dist: pandas
Requires-Dist: numpy
